{
   "agent": "spray-websocket-client",
   "behavior": "OK",
   "behaviorClose": "OK",
   "case": 323,
   "closedByMe": true,
   "createStats": true,
   "createWirelog": true,
   "description": "Send 1000 messages of payload size 32768 to measure implementation/network RTT (round trip time) / latency.",
   "droppedByMe": true,
   "duration": 10066,
   "expectation": "Receive echo'ed messages (with payload as sent). Timeout case after 480 secs.",
   "expected": {},
   "expectedClose": {
      "closeCode": [
         1000
      ],
      "closedByMe": true,
      "requireClean": true
   },
   "failedByMe": false,
   "httpRequest": "GET /runCase?case=323&agent=spray-websocket-client HTTP/1.1\r\nHost: 127.0.0.1:9001\r\nConnection: Upgrade\r\nUpgrade: websocket\r\nSec-WebSocket-Version: 13\r\nSec-WebSocket-Key: x3JJHMbDL1EzLkh9GBhXDw==\r\nSec-WebSocket-Extensions: permessage-deflate\r\nUser-Agent: spray-can/1.3-RC1\r\n\r\n",
   "httpResponse": "HTTP/1.1 101 Switching Protocols\r\nServer: AutobahnTestSuite/0.5.7-0.7.4\r\nUpgrade: WebSocket\r\nConnection: Upgrade\r\nSec-WebSocket-Accept: HSmrc0sMlYUkAGmm5OPpG2HaGWk=\r\nSec-WebSocket-Extensions: permessage-deflate\r\n\r\n",
   "id": "12.2.8",
   "isServer": true,
   "localCloseCode": 1000,
   "localCloseReason": null,
   "received": [],
   "remoteCloseCode": 1000,
   "remoteCloseReason": null,
   "reportCompressionRatio": true,
   "reportTime": true,
   "result": "Ok, received all echo'ed messages in time.",
   "resultClose": "Connection was properly closed",
   "rxFrameStats": {
      "2": 1000,
      "8": 1
   },
   "rxOctetStats": {
      "1": 2001,
      "7": 1,
      "275": 1,
      "7025": 1,
      "7028": 1,
      "7037": 1,
      "7127": 1,
      "7198": 1,
      "7240": 1,
      "7254": 1,
      "7276": 1,
      "7314": 1,
      "7388": 1,
      "7390": 1,
      "7398": 1,
      "7411": 1,
      "7421": 1,
      "7427": 1,
      "7435": 1,
      "7443": 1,
      "7463": 1,
      "7506": 1,
      "7509": 1,
      "7528": 1,
      "7534": 1,
      "7556": 1,
      "7567": 1,
      "7606": 1,
      "7647": 1,
      "7689": 1,
      "7707": 1,
      "7724": 1,
      "7733": 1,
      "7767": 1,
      "7793": 1,
      "7813": 1,
      "7848": 1,
      "7893": 1,
      "7902": 1,
      "7930": 1,
      "7947": 1,
      "7999": 1,
      "8047": 1,
      "8077": 1,
      "8084": 1,
      "8107": 1,
      "8150": 1,
      "8226": 1,
      "8232": 1,
      "8251": 1,
      "8267": 1,
      "8313": 1,
      "8383": 1,
      "8413": 1,
      "8423": 1,
      "8445": 1,
      "8478": 1,
      "8540": 1,
      "8546": 1,
      "8590": 1,
      "8608": 1,
      "8628": 1,
      "8694": 1,
      "8717": 1,
      "8766": 1,
      "8776": 1,
      "8791": 1,
      "8849": 1,
      "8871": 1,
      "8910": 1,
      "8943": 1,
      "8961": 1,
      "8999": 1,
      "9035": 1,
      "9061": 1,
      "9064": 1,
      "9085": 1,
      "9106": 1,
      "9136": 1,
      "9145": 1,
      "9161": 1,
      "9179": 1,
      "9182": 1,
      "9198": 1,
      "9210": 1,
      "9237": 1,
      "9251": 1,
      "9286": 1,
      "9300": 1,
      "9337": 1,
      "9340": 1,
      "9358": 1,
      "9360": 1,
      "9396": 1,
      "9404": 1,
      "9451": 1,
      "9459": 1,
      "9484": 1,
      "9493": 1,
      "9501": 1,
      "9521": 1,
      "9533": 1,
      "9570": 1,
      "9600": 1,
      "9622": 2,
      "9651": 1,
      "9666": 1,
      "9677": 1,
      "9691": 1,
      "9716": 1,
      "9757": 1,
      "9768": 1,
      "9785": 1,
      "9798": 1,
      "9824": 1,
      "9826": 1,
      "9850": 1,
      "9859": 1,
      "9908": 1,
      "9918": 1,
      "9936": 1,
      "9945": 1,
      "9970": 1,
      "9986": 1,
      "9997": 1,
      "10002": 1,
      "10058": 1,
      "10078": 1,
      "10085": 1,
      "10108": 1,
      "10129": 1,
      "10132": 1,
      "10144": 1,
      "10152": 1,
      "10207": 1,
      "10220": 1,
      "10236": 1,
      "10260": 1,
      "10272": 1,
      "10282": 1,
      "10303": 1,
      "10308": 1,
      "10345": 1,
      "10355": 1,
      "10381": 1,
      "10395": 1,
      "10421": 1,
      "10423": 1,
      "10433": 1,
      "10450": 1,
      "10480": 1,
      "10498": 1,
      "10500": 1,
      "10513": 1,
      "10540": 2,
      "10560": 1,
      "10583": 1,
      "10612": 2,
      "10628": 1,
      "10656": 1,
      "10674": 1,
      "10687": 1,
      "10703": 1,
      "10716": 1,
      "10718": 1,
      "10723": 1,
      "10760": 1,
      "10772": 1,
      "10776": 1,
      "10780": 1,
      "10806": 1,
      "10831": 1,
      "10851": 1,
      "10887": 1,
      "10900": 1,
      "10913": 1,
      "10983": 1,
      "11009": 1,
      "11051": 1,
      "11078": 1,
      "11096": 1,
      "11145": 1,
      "11168": 1,
      "11209": 1,
      "11226": 1,
      "11264": 1,
      "11284": 1,
      "11305": 1,
      "11354": 1,
      "11356": 1,
      "11417": 1,
      "11452": 1,
      "11466": 1,
      "11477": 1,
      "11487": 1,
      "11539": 1,
      "11581": 1,
      "11597": 1,
      "11618": 1,
      "11655": 1,
      "11660": 1,
      "11712": 1,
      "11716": 1,
      "11758": 1,
      "11778": 1,
      "11833": 1,
      "11836": 1,
      "11839": 1,
      "11892": 1,
      "11921": 1,
      "11946": 1,
      "11960": 1,
      "11997": 1,
      "12022": 1,
      "12032": 1,
      "12050": 1,
      "12063": 1,
      "12088": 1,
      "12120": 1,
      "12122": 1,
      "12154": 1,
      "12176": 1,
      "12183": 2,
      "12184": 1,
      "12190": 1,
      "12191": 1,
      "12192": 4,
      "12195": 2,
      "12196": 1,
      "12200": 3,
      "12202": 1,
      "12208": 1,
      "12209": 2,
      "12211": 3,
      "12213": 1,
      "12214": 1,
      "12215": 1,
      "12216": 1,
      "12218": 1,
      "12222": 1,
      "12223": 1,
      "12229": 2,
      "12232": 1,
      "12240": 1,
      "12241": 1,
      "12243": 3,
      "12244": 1,
      "12251": 2,
      "12256": 1,
      "12261": 1,
      "12264": 1,
      "12269": 2,
      "12271": 1,
      "12274": 1,
      "12277": 1,
      "12280": 2,
      "12281": 1,
      "12284": 1,
      "12286": 1,
      "12290": 1,
      "12291": 1,
      "12294": 1,
      "12300": 1,
      "12301": 1,
      "12303": 1,
      "12305": 2,
      "12306": 1,
      "12310": 3,
      "12312": 2,
      "12313": 1,
      "12315": 2,
      "12316": 1,
      "12320": 2,
      "12321": 2,
      "12324": 1,
      "12326": 1,
      "12330": 1,
      "12332": 2,
      "12336": 2,
      "12337": 1,
      "12341": 1,
      "12342": 1,
      "12343": 1,
      "12344": 1,
      "12345": 1,
      "12346": 1,
      "12347": 1,
      "12348": 2,
      "12351": 1,
      "12352": 1,
      "12353": 2,
      "12354": 1,
      "12356": 1,
      "12358": 1,
      "12359": 1,
      "12361": 1,
      "12362": 4,
      "12363": 2,
      "12364": 1,
      "12365": 1,
      "12367": 1,
      "12368": 3,
      "12369": 2,
      "12370": 1,
      "12371": 1,
      "12373": 1,
      "12375": 1,
      "12376": 1,
      "12377": 2,
      "12379": 2,
      "12381": 1,
      "12383": 1,
      "12385": 1,
      "12386": 1,
      "12390": 1,
      "12393": 1,
      "12396": 1,
      "12397": 1,
      "12400": 2,
      "12401": 1,
      "12402": 3,
      "12404": 1,
      "12407": 1,
      "12408": 1,
      "12410": 2,
      "12411": 1,
      "12412": 3,
      "12413": 1,
      "12416": 1,
      "12417": 1,
      "12419": 2,
      "12424": 3,
      "12425": 1,
      "12427": 1,
      "12428": 3,
      "12430": 1,
      "12431": 1,
      "12432": 1,
      "12434": 1,
      "12438": 2,
      "12441": 2,
      "12443": 4,
      "12447": 1,
      "12449": 2,
      "12453": 1,
      "12458": 1,
      "12459": 1,
      "12460": 1,
      "12462": 1,
      "12466": 1,
      "12468": 3,
      "12469": 1,
      "12470": 2,
      "12471": 1,
      "12475": 1,
      "12478": 1,
      "12482": 1,
      "12484": 1,
      "12488": 1,
      "12489": 1,
      "12492": 3,
      "12494": 1,
      "12498": 1,
      "12499": 1,
      "12501": 1,
      "12506": 2,
      "12514": 1,
      "12518": 2,
      "12523": 1,
      "12525": 1,
      "12528": 1,
      "12529": 3,
      "12530": 1,
      "12532": 3,
      "12534": 1,
      "12537": 1,
      "12540": 1,
      "12541": 1,
      "12542": 1,
      "12544": 2,
      "12547": 1,
      "12548": 1,
      "12549": 2,
      "12552": 1,
      "12555": 1,
      "12557": 1,
      "12561": 1,
      "12564": 1,
      "12568": 1,
      "12570": 2,
      "12573": 1,
      "12577": 1,
      "12578": 1,
      "12580": 1,
      "12581": 1,
      "12582": 1,
      "12588": 1,
      "12590": 1,
      "12591": 1,
      "12593": 1,
      "12594": 1,
      "12595": 1,
      "12598": 2,
      "12600": 2,
      "12607": 3,
      "12610": 4,
      "12611": 1,
      "12619": 2,
      "12620": 1,
      "12621": 1,
      "12627": 1,
      "12628": 2,
      "12630": 2,
      "12633": 2,
      "12635": 1,
      "12636": 1,
      "12637": 2,
      "12638": 2,
      "12639": 4,
      "12641": 1,
      "12642": 1,
      "12645": 1,
      "12650": 1,
      "12652": 1,
      "12656": 1,
      "12657": 1,
      "12658": 2,
      "12659": 2,
      "12663": 1,
      "12664": 2,
      "12666": 1,
      "12669": 2,
      "12673": 2,
      "12674": 1,
      "12676": 1,
      "12677": 1,
      "12678": 4,
      "12679": 1,
      "12681": 1,
      "12682": 4,
      "12683": 3,
      "12684": 1,
      "12685": 2,
      "12686": 4,
      "12687": 2,
      "12688": 3,
      "12689": 1,
      "12690": 2,
      "12691": 2,
      "12692": 1,
      "12694": 2,
      "12695": 1,
      "12696": 1,
      "12697": 2,
      "12699": 1,
      "12700": 1,
      "12701": 1,
      "12704": 1,
      "12705": 1,
      "12707": 1,
      "12708": 2,
      "12709": 3,
      "12710": 2,
      "12711": 1,
      "12712": 1,
      "12713": 1,
      "12714": 1,
      "12715": 1,
      "12716": 2,
      "12718": 1,
      "12720": 1,
      "12722": 2,
      "12723": 1,
      "12724": 4,
      "12725": 1,
      "12726": 3,
      "12727": 1,
      "12728": 2,
      "12729": 2,
      "12730": 3,
      "12731": 5,
      "12733": 3,
      "12734": 1,
      "12735": 2,
      "12736": 1,
      "12737": 1,
      "12738": 2,
      "12740": 3,
      "12741": 1,
      "12744": 2,
      "12746": 1,
      "12747": 6,
      "12750": 2,
      "12751": 1,
      "12752": 2,
      "12753": 2,
      "12754": 2,
      "12756": 4,
      "12757": 1,
      "12758": 2,
      "12759": 4,
      "12760": 3,
      "12761": 1,
      "12762": 1,
      "12763": 1,
      "12766": 2,
      "12767": 1,
      "12769": 2,
      "12770": 1,
      "12771": 1,
      "12772": 3,
      "12773": 3,
      "12775": 3,
      "12776": 1,
      "12777": 3,
      "12778": 4,
      "12779": 3,
      "12780": 4,
      "12781": 3,
      "12782": 1,
      "12783": 3,
      "12785": 1,
      "12787": 1,
      "12788": 5,
      "12789": 1,
      "12790": 2,
      "12791": 1,
      "12792": 3,
      "12793": 1,
      "12794": 1,
      "12795": 4,
      "12796": 2,
      "12797": 1,
      "12798": 2,
      "12799": 1,
      "12800": 4,
      "12801": 1,
      "12802": 1,
      "12803": 1,
      "12805": 1,
      "12806": 2,
      "12808": 1,
      "12809": 2,
      "12812": 1,
      "12814": 1,
      "12816": 1,
      "12818": 1,
      "12819": 1,
      "12826": 1,
      "12827": 1,
      "12828": 1,
      "12830": 1,
      "12833": 3,
      "12834": 1,
      "12837": 1,
      "12840": 1,
      "12841": 1,
      "12843": 1,
      "12846": 2,
      "12850": 1,
      "12854": 1,
      "12855": 1,
      "12858": 1,
      "12861": 1,
      "12862": 1,
      "12863": 1,
      "12864": 1,
      "12868": 1,
      "12871": 1,
      "12874": 2,
      "12875": 1,
      "12876": 2,
      "12879": 2,
      "12880": 1,
      "12882": 4,
      "12883": 3,
      "12884": 3,
      "12885": 1,
      "12886": 2,
      "12887": 1,
      "12889": 3,
      "12890": 2,
      "12891": 1,
      "12893": 2,
      "12894": 1,
      "12896": 3,
      "12897": 2,
      "12902": 1,
      "12905": 2,
      "12906": 3,
      "12908": 3,
      "12909": 2,
      "12910": 3,
      "12911": 1,
      "12913": 1,
      "12914": 1,
      "12915": 2,
      "12916": 1,
      "12917": 1,
      "12918": 1,
      "12919": 2,
      "12920": 1,
      "12921": 1,
      "12922": 2,
      "12923": 2,
      "12924": 1,
      "12925": 2,
      "12928": 1,
      "12931": 1,
      "12934": 1,
      "12936": 1,
      "12938": 1,
      "12939": 1,
      "12941": 1,
      "12942": 2,
      "12943": 1,
      "12947": 3,
      "12948": 1,
      "12949": 1,
      "12950": 1,
      "12952": 1,
      "12953": 3,
      "12954": 2,
      "12958": 3,
      "12960": 2,
      "12961": 2,
      "12962": 2,
      "12963": 2,
      "12966": 3,
      "12968": 1,
      "12970": 1,
      "12971": 2,
      "12973": 1,
      "12974": 1,
      "12975": 1,
      "12976": 1,
      "12978": 1,
      "12980": 2,
      "12981": 1,
      "12982": 2,
      "12983": 1,
      "12984": 1,
      "12985": 2,
      "12986": 1,
      "12987": 2,
      "12989": 1,
      "12990": 1,
      "12991": 1,
      "12993": 1,
      "12995": 2,
      "12996": 1,
      "12997": 1,
      "12999": 1,
      "13000": 3,
      "13003": 1,
      "13005": 1,
      "13006": 1,
      "13007": 1,
      "13008": 1,
      "13009": 5,
      "13010": 2,
      "13011": 2,
      "13012": 2,
      "13014": 1,
      "13015": 1,
      "13016": 1,
      "13017": 1,
      "13018": 3,
      "13019": 1,
      "13020": 1,
      "13022": 3,
      "13023": 1,
      "13024": 2,
      "13025": 3,
      "13026": 3,
      "13027": 1,
      "13028": 1,
      "13029": 3,
      "13030": 3,
      "13031": 4,
      "13032": 7,
      "13033": 2,
      "13034": 1,
      "13035": 1,
      "13036": 1,
      "13037": 3,
      "13038": 2,
      "13039": 3,
      "13040": 3,
      "13041": 2,
      "13042": 1,
      "13044": 1,
      "13046": 1,
      "13047": 2,
      "13048": 3,
      "13049": 1,
      "13052": 7,
      "13054": 1,
      "13059": 1,
      "13060": 3,
      "13061": 1,
      "13067": 1,
      "13069": 2,
      "13071": 1,
      "15846": 1000
   },
   "started": "2014-03-01T05:27:39Z",
   "trafficStats": {
      "incomingCompressionRatio": 0.8505317077636719,
      "incomingOctetsAppLevel": 32768000,
      "incomingOctetsWebSocketLevel": 27870223,
      "incomingOctetsWireLevel": 27878223,
      "incomingWebSocketFrames": 1000,
      "incomingWebSocketMessages": 1000,
      "incomingWebSocketOverhead": 0.00028704470717726225,
      "outgoingCompressionRatio": 0.8505317077636719,
      "outgoingOctetsAppLevel": 32768000,
      "outgoingOctetsWebSocketLevel": 27870223,
      "outgoingOctetsWireLevel": 27874223,
      "outgoingWebSocketFrames": 1000,
      "outgoingWebSocketMessages": 1000,
      "outgoingWebSocketOverhead": 0.00014352235358863112,
      "preopenIncomingOctetsWireLevel": 275,
      "preopenOutgoingOctetsWireLevel": 214
   },
   "txFrameStats": {
      "2": 1000,
      "8": 1
   },
   "txOctetStats": {
      "4": 1,
      "214": 1,
      "22869": 1,
      "22872": 1,
      "22881": 1,
      "22971": 1,
      "23042": 1,
      "23084": 1,
      "23098": 1,
      "23120": 1,
      "23158": 1,
      "23232": 1,
      "23234": 1,
      "23242": 1,
      "23255": 1,
      "23265": 1,
      "23271": 1,
      "23279": 1,
      "23287": 1,
      "23307": 1,
      "23350": 1,
      "23353": 1,
      "23372": 1,
      "23378": 1,
      "23400": 1,
      "23411": 1,
      "23450": 1,
      "23491": 1,
      "23533": 1,
      "23551": 1,
      "23568": 1,
      "23577": 1,
      "23611": 1,
      "23637": 1,
      "23657": 1,
      "23692": 1,
      "23737": 1,
      "23746": 1,
      "23774": 1,
      "23791": 1,
      "23843": 1,
      "23891": 1,
      "23921": 1,
      "23928": 1,
      "23951": 1,
      "23994": 1,
      "24070": 1,
      "24076": 1,
      "24095": 1,
      "24111": 1,
      "24157": 1,
      "24227": 1,
      "24257": 1,
      "24267": 1,
      "24289": 1,
      "24322": 1,
      "24384": 1,
      "24390": 1,
      "24434": 1,
      "24452": 1,
      "24472": 1,
      "24538": 1,
      "24561": 1,
      "24610": 1,
      "24620": 1,
      "24635": 1,
      "24693": 1,
      "24715": 1,
      "24754": 1,
      "24787": 1,
      "24805": 1,
      "24843": 1,
      "24879": 1,
      "24905": 1,
      "24908": 1,
      "24929": 1,
      "24950": 1,
      "24980": 1,
      "24989": 1,
      "25005": 1,
      "25023": 1,
      "25026": 1,
      "25042": 1,
      "25054": 1,
      "25081": 1,
      "25095": 1,
      "25130": 1,
      "25144": 1,
      "25181": 1,
      "25184": 1,
      "25202": 1,
      "25204": 1,
      "25240": 1,
      "25248": 1,
      "25295": 1,
      "25303": 1,
      "25328": 1,
      "25337": 1,
      "25345": 1,
      "25365": 1,
      "25377": 1,
      "25414": 1,
      "25444": 1,
      "25466": 2,
      "25495": 1,
      "25510": 1,
      "25521": 1,
      "25535": 1,
      "25560": 1,
      "25601": 1,
      "25612": 1,
      "25629": 1,
      "25642": 1,
      "25668": 1,
      "25670": 1,
      "25694": 1,
      "25703": 1,
      "25752": 1,
      "25762": 1,
      "25780": 1,
      "25789": 1,
      "25814": 1,
      "25830": 1,
      "25841": 1,
      "25846": 1,
      "25902": 1,
      "25922": 1,
      "25929": 1,
      "25952": 1,
      "25973": 1,
      "25976": 1,
      "25988": 1,
      "25996": 1,
      "26051": 1,
      "26064": 1,
      "26080": 1,
      "26104": 1,
      "26116": 1,
      "26126": 1,
      "26147": 1,
      "26152": 1,
      "26189": 1,
      "26199": 1,
      "26225": 1,
      "26239": 1,
      "26265": 1,
      "26267": 1,
      "26277": 1,
      "26294": 1,
      "26324": 1,
      "26342": 1,
      "26344": 1,
      "26357": 1,
      "26384": 2,
      "26404": 1,
      "26427": 1,
      "26456": 2,
      "26472": 1,
      "26500": 1,
      "26518": 1,
      "26531": 1,
      "26547": 1,
      "26560": 1,
      "26562": 1,
      "26567": 1,
      "26604": 1,
      "26616": 1,
      "26620": 1,
      "26624": 1,
      "26650": 1,
      "26675": 1,
      "26695": 1,
      "26731": 1,
      "26744": 1,
      "26757": 1,
      "26827": 1,
      "26853": 1,
      "26895": 1,
      "26922": 1,
      "26940": 1,
      "26989": 1,
      "27012": 1,
      "27053": 1,
      "27070": 1,
      "27108": 1,
      "27128": 1,
      "27149": 1,
      "27198": 1,
      "27200": 1,
      "27261": 1,
      "27296": 1,
      "27310": 1,
      "27321": 1,
      "27331": 1,
      "27383": 1,
      "27425": 1,
      "27441": 1,
      "27462": 1,
      "27499": 1,
      "27504": 1,
      "27556": 1,
      "27560": 1,
      "27602": 1,
      "27622": 1,
      "27677": 1,
      "27680": 1,
      "27683": 1,
      "27736": 1,
      "27765": 1,
      "27790": 1,
      "27804": 1,
      "27841": 1,
      "27866": 1,
      "27876": 1,
      "27894": 1,
      "27907": 1,
      "27932": 1,
      "27964": 1,
      "27966": 1,
      "27998": 1,
      "28020": 1,
      "28027": 2,
      "28028": 1,
      "28034": 1,
      "28035": 1,
      "28036": 4,
      "28039": 2,
      "28040": 1,
      "28044": 3,
      "28046": 1,
      "28052": 1,
      "28053": 2,
      "28055": 3,
      "28057": 1,
      "28058": 1,
      "28059": 1,
      "28060": 1,
      "28062": 1,
      "28066": 1,
      "28067": 1,
      "28073": 2,
      "28076": 1,
      "28084": 1,
      "28085": 1,
      "28087": 3,
      "28088": 1,
      "28095": 2,
      "28100": 1,
      "28105": 1,
      "28108": 1,
      "28113": 2,
      "28115": 1,
      "28118": 1,
      "28121": 1,
      "28124": 2,
      "28125": 1,
      "28128": 1,
      "28130": 1,
      "28134": 1,
      "28135": 1,
      "28138": 1,
      "28144": 1,
      "28145": 1,
      "28147": 1,
      "28149": 2,
      "28150": 1,
      "28154": 3,
      "28156": 2,
      "28157": 1,
      "28159": 2,
      "28160": 1,
      "28164": 2,
      "28165": 2,
      "28168": 1,
      "28170": 1,
      "28174": 1,
      "28176": 2,
      "28180": 2,
      "28181": 1,
      "28185": 1,
      "28186": 1,
      "28187": 1,
      "28188": 1,
      "28189": 1,
      "28190": 1,
      "28191": 1,
      "28192": 2,
      "28195": 1,
      "28196": 1,
      "28197": 2,
      "28198": 1,
      "28200": 1,
      "28202": 1,
      "28203": 1,
      "28205": 1,
      "28206": 4,
      "28207": 2,
      "28208": 1,
      "28209": 1,
      "28211": 1,
      "28212": 3,
      "28213": 2,
      "28214": 1,
      "28215": 1,
      "28217": 1,
      "28219": 1,
      "28220": 1,
      "28221": 2,
      "28223": 2,
      "28225": 1,
      "28227": 1,
      "28229": 1,
      "28230": 1,
      "28234": 1,
      "28237": 1,
      "28240": 1,
      "28241": 1,
      "28244": 2,
      "28245": 1,
      "28246": 3,
      "28248": 1,
      "28251": 1,
      "28252": 1,
      "28254": 2,
      "28255": 1,
      "28256": 3,
      "28257": 1,
      "28260": 1,
      "28261": 1,
      "28263": 2,
      "28268": 3,
      "28269": 1,
      "28271": 1,
      "28272": 3,
      "28274": 1,
      "28275": 1,
      "28276": 1,
      "28278": 1,
      "28282": 2,
      "28285": 2,
      "28287": 4,
      "28291": 1,
      "28293": 2,
      "28297": 1,
      "28302": 1,
      "28303": 1,
      "28304": 1,
      "28306": 1,
      "28310": 1,
      "28312": 3,
      "28313": 1,
      "28314": 2,
      "28315": 1,
      "28319": 1,
      "28322": 1,
      "28326": 1,
      "28328": 1,
      "28332": 1,
      "28333": 1,
      "28336": 3,
      "28338": 1,
      "28342": 1,
      "28343": 1,
      "28345": 1,
      "28350": 2,
      "28358": 1,
      "28362": 2,
      "28367": 1,
      "28369": 1,
      "28372": 1,
      "28373": 3,
      "28374": 1,
      "28376": 3,
      "28378": 1,
      "28381": 1,
      "28384": 1,
      "28385": 1,
      "28386": 1,
      "28388": 2,
      "28391": 1,
      "28392": 1,
      "28393": 2,
      "28396": 1,
      "28399": 1,
      "28401": 1,
      "28405": 1,
      "28408": 1,
      "28412": 1,
      "28414": 2,
      "28417": 1,
      "28421": 1,
      "28422": 1,
      "28424": 1,
      "28425": 1,
      "28426": 1,
      "28432": 1,
      "28434": 1,
      "28435": 1,
      "28437": 1,
      "28438": 1,
      "28439": 1,
      "28442": 2,
      "28444": 2,
      "28451": 3,
      "28454": 4,
      "28455": 1,
      "28463": 2,
      "28464": 1,
      "28465": 1,
      "28471": 1,
      "28472": 2,
      "28474": 2,
      "28477": 2,
      "28479": 1,
      "28480": 1,
      "28481": 2,
      "28482": 2,
      "28483": 4,
      "28485": 1,
      "28486": 1,
      "28489": 1,
      "28494": 1,
      "28496": 1,
      "28500": 1,
      "28501": 1,
      "28502": 2,
      "28503": 2,
      "28507": 1,
      "28508": 2,
      "28510": 1,
      "28513": 2,
      "28517": 2,
      "28518": 1,
      "28520": 1,
      "28521": 1,
      "28522": 4,
      "28523": 1,
      "28525": 1,
      "28526": 4,
      "28527": 3,
      "28528": 1,
      "28529": 2,
      "28530": 4,
      "28531": 2,
      "28532": 3,
      "28533": 1,
      "28534": 2,
      "28535": 2,
      "28536": 1,
      "28538": 2,
      "28539": 1,
      "28540": 1,
      "28541": 2,
      "28543": 1,
      "28544": 1,
      "28545": 1,
      "28548": 1,
      "28549": 1,
      "28551": 1,
      "28552": 2,
      "28553": 3,
      "28554": 2,
      "28555": 1,
      "28556": 1,
      "28557": 1,
      "28558": 1,
      "28559": 1,
      "28560": 2,
      "28562": 1,
      "28564": 1,
      "28566": 2,
      "28567": 1,
      "28568": 4,
      "28569": 1,
      "28570": 3,
      "28571": 1,
      "28572": 2,
      "28573": 2,
      "28574": 3,
      "28575": 5,
      "28577": 3,
      "28578": 1,
      "28579": 2,
      "28580": 1,
      "28581": 1,
      "28582": 2,
      "28584": 3,
      "28585": 1,
      "28588": 2,
      "28590": 1,
      "28591": 6,
      "28594": 2,
      "28595": 1,
      "28596": 2,
      "28597": 2,
      "28598": 2,
      "28600": 4,
      "28601": 1,
      "28602": 2,
      "28603": 4,
      "28604": 3,
      "28605": 1,
      "28606": 1,
      "28607": 1,
      "28610": 2,
      "28611": 1,
      "28613": 2,
      "28614": 1,
      "28615": 1,
      "28616": 3,
      "28617": 3,
      "28619": 3,
      "28620": 1,
      "28621": 3,
      "28622": 4,
      "28623": 3,
      "28624": 4,
      "28625": 3,
      "28626": 1,
      "28627": 3,
      "28629": 1,
      "28631": 1,
      "28632": 5,
      "28633": 1,
      "28634": 2,
      "28635": 1,
      "28636": 3,
      "28637": 1,
      "28638": 1,
      "28639": 4,
      "28640": 2,
      "28641": 1,
      "28642": 2,
      "28643": 1,
      "28644": 4,
      "28645": 1,
      "28646": 1,
      "28647": 1,
      "28649": 1,
      "28650": 2,
      "28652": 1,
      "28653": 2,
      "28656": 1,
      "28658": 1,
      "28660": 1,
      "28662": 1,
      "28663": 1,
      "28670": 1,
      "28671": 1,
      "28672": 1,
      "28674": 1,
      "28677": 3,
      "28678": 1,
      "28681": 1,
      "28684": 1,
      "28685": 1,
      "28687": 1,
      "28690": 2,
      "28694": 1,
      "28698": 1,
      "28699": 1,
      "28702": 1,
      "28705": 1,
      "28706": 1,
      "28707": 1,
      "28708": 1,
      "28712": 1,
      "28715": 1,
      "28718": 2,
      "28719": 1,
      "28720": 2,
      "28723": 2,
      "28724": 1,
      "28726": 4,
      "28727": 3,
      "28728": 3,
      "28729": 1,
      "28730": 2,
      "28731": 1,
      "28733": 3,
      "28734": 2,
      "28735": 1,
      "28737": 2,
      "28738": 1,
      "28740": 3,
      "28741": 2,
      "28746": 1,
      "28749": 2,
      "28750": 3,
      "28752": 3,
      "28753": 2,
      "28754": 3,
      "28755": 1,
      "28757": 1,
      "28758": 1,
      "28759": 2,
      "28760": 1,
      "28761": 1,
      "28762": 1,
      "28763": 2,
      "28764": 1,
      "28765": 1,
      "28766": 2,
      "28767": 2,
      "28768": 1,
      "28769": 2,
      "28772": 1,
      "28775": 1,
      "28778": 1,
      "28780": 1,
      "28782": 1,
      "28783": 1,
      "28785": 1,
      "28786": 2,
      "28787": 1,
      "28791": 3,
      "28792": 1,
      "28793": 1,
      "28794": 1,
      "28796": 1,
      "28797": 3,
      "28798": 2,
      "28802": 3,
      "28804": 2,
      "28805": 2,
      "28806": 2,
      "28807": 2,
      "28810": 3,
      "28812": 1,
      "28814": 1,
      "28815": 2,
      "28817": 1,
      "28818": 1,
      "28819": 1,
      "28820": 1,
      "28822": 1,
      "28824": 2,
      "28825": 1,
      "28826": 2,
      "28827": 1,
      "28828": 1,
      "28829": 2,
      "28830": 1,
      "28831": 2,
      "28833": 1,
      "28834": 1,
      "28835": 1,
      "28837": 1,
      "28839": 2,
      "28840": 1,
      "28841": 1,
      "28843": 1,
      "28844": 3,
      "28847": 1,
      "28849": 1,
      "28850": 1,
      "28851": 1,
      "28852": 1,
      "28853": 5,
      "28854": 2,
      "28855": 2,
      "28856": 2,
      "28858": 1,
      "28859": 1,
      "28860": 1,
      "28861": 1,
      "28862": 3,
      "28863": 1,
      "28864": 1,
      "28866": 3,
      "28867": 1,
      "28868": 2,
      "28869": 3,
      "28870": 3,
      "28871": 1,
      "28872": 1,
      "28873": 3,
      "28874": 3,
      "28875": 4,
      "28876": 7,
      "28877": 2,
      "28878": 1,
      "28879": 1,
      "28880": 1,
      "28881": 3,
      "28882": 2,
      "28883": 3,
      "28884": 3,
      "28885": 2,
      "28886": 1,
      "28888": 1,
      "28890": 1,
      "28891": 2,
      "28892": 3,
      "28893": 1,
      "28896": 7,
      "28898": 1,
      "28903": 1,
      "28904": 3,
      "28905": 1,
      "28911": 1,
      "28913": 2,
      "28915": 1
   },
   "wasClean": true,
   "wasCloseHandshakeTimeout": false,
   "wasNotCleanReason": null,
   "wasOpenHandshakeTimeout": false,
   "wasServerConnectionDropTimeout": false,
   "wirelog": [
      [
         "RO",
         [
            275,
            "474554202f72756e436173653f636173653d333233266167656e743d73707261792d776562736f636b65742d636c69656e7420485454502f312e310d0a486f73 ..."
         ]
      ],
      [
         "TO",
         [
            214,
            "485454502f312e312031303120537769746368696e672050726f746f636f6c730d0a5365727665723a204175746f6261686e5465737453756974652f302e352e ..."
         ],
         false
      ],
      [
         "WLM",
         false
      ],
      [
         "TI",
         480
      ],
      [
         "WLM",
         true
      ],
      [
         "TF",
         [
            2,
            "0x03e8"
         ],
         8,
         true,
         0,
         null,
         null,
         null,
         false
      ],
      [
         "TO",
         [
            4,
            "880203e8"
         ],
         false
      ],
      [
         "RO",
         [
            1,
            "88"
         ]
      ],
      [
         "RO",
         [
            7,
            "82407ea0fb4396"
         ]
      ],
      [
         "RF",
         [
            2,
            "0x03e8"
         ],
         8,
         true,
         0,
         true,
         "407ea0fb"
      ]
   ]
}