{
   "agent": "spray-websocket-client",
   "behavior": "OK",
   "behaviorClose": "OK",
   "case": 331,
   "closedByMe": true,
   "createStats": true,
   "createWirelog": true,
   "description": "Send 1000 messages of payload size 8192 to measure implementation/network RTT (round trip time) / latency.",
   "droppedByMe": true,
   "duration": 2988,
   "expectation": "Receive echo'ed messages (with payload as sent). Timeout case after 480 secs.",
   "expected": {},
   "expectedClose": {
      "closeCode": [
         1000
      ],
      "closedByMe": true,
      "requireClean": true
   },
   "failedByMe": false,
   "httpRequest": "GET /runCase?case=331&agent=spray-websocket-client HTTP/1.1\r\nHost: 127.0.0.1:9001\r\nConnection: Upgrade\r\nUpgrade: websocket\r\nSec-WebSocket-Version: 13\r\nSec-WebSocket-Key: x3JJHMbDL1EzLkh9GBhXDw==\r\nSec-WebSocket-Extensions: permessage-deflate\r\nUser-Agent: spray-can/1.3-RC1\r\n\r\n",
   "httpResponse": "HTTP/1.1 101 Switching Protocols\r\nServer: AutobahnTestSuite/0.5.7-0.7.4\r\nUpgrade: WebSocket\r\nConnection: Upgrade\r\nSec-WebSocket-Accept: HSmrc0sMlYUkAGmm5OPpG2HaGWk=\r\nSec-WebSocket-Extensions: permessage-deflate\r\n\r\n",
   "id": "12.3.6",
   "isServer": true,
   "localCloseCode": 1000,
   "localCloseReason": null,
   "received": [],
   "remoteCloseCode": 1000,
   "remoteCloseReason": null,
   "reportCompressionRatio": true,
   "reportTime": true,
   "result": "Ok, received all echo'ed messages in time.",
   "resultClose": "Connection was properly closed",
   "rxFrameStats": {
      "2": 1000,
      "8": 1
   },
   "rxOctetStats": {
      "1": 1001,
      "7": 1,
      "275": 1,
      "2525": 1,
      "2527": 1,
      "2531": 1,
      "2544": 1,
      "2554": 1,
      "2557": 1,
      "2558": 1,
      "2596": 1,
      "2597": 2,
      "2646": 1,
      "2647": 1,
      "2649": 1,
      "2695": 1,
      "2733": 1,
      "2748": 1,
      "2759": 1,
      "2761": 1,
      "2763": 1,
      "2767": 1,
      "2780": 1,
      "2783": 1,
      "2785": 1,
      "2798": 1,
      "2799": 1,
      "2804": 1,
      "2807": 1,
      "2834": 1,
      "2838": 1,
      "2844": 1,
      "2848": 1,
      "2859": 1,
      "2872": 1,
      "2882": 1,
      "2885": 1,
      "2886": 1,
      "2889": 1,
      "2899": 1,
      "2900": 2,
      "2904": 4,
      "2905": 2,
      "2908": 3,
      "2909": 1,
      "2914": 3,
      "2916": 1,
      "2917": 1,
      "2920": 1,
      "2922": 1,
      "2923": 3,
      "2926": 2,
      "2927": 1,
      "2930": 2,
      "2932": 1,
      "2934": 1,
      "2935": 1,
      "2936": 1,
      "2937": 1,
      "2939": 3,
      "2940": 6,
      "2941": 4,
      "2942": 5,
      "2943": 1,
      "2944": 1,
      "2945": 2,
      "2946": 1,
      "2947": 2,
      "2948": 2,
      "2949": 2,
      "2950": 1,
      "2951": 4,
      "2953": 6,
      "2954": 1,
      "2955": 1,
      "2956": 1,
      "2957": 1,
      "2958": 1,
      "2959": 4,
      "2960": 2,
      "2961": 3,
      "2962": 2,
      "2963": 2,
      "2964": 2,
      "2965": 2,
      "2967": 1,
      "2969": 4,
      "2971": 1,
      "2972": 2,
      "2973": 1,
      "2974": 5,
      "2975": 1,
      "2976": 1,
      "2977": 2,
      "2978": 2,
      "2979": 2,
      "2980": 4,
      "2982": 3,
      "2983": 2,
      "2984": 4,
      "2985": 3,
      "2986": 6,
      "2987": 2,
      "2988": 4,
      "2989": 2,
      "2990": 2,
      "2991": 5,
      "2992": 1,
      "2993": 1,
      "2994": 5,
      "2995": 5,
      "2996": 8,
      "2997": 6,
      "2998": 2,
      "2999": 6,
      "3000": 3,
      "3001": 4,
      "3002": 4,
      "3003": 3,
      "3004": 4,
      "3005": 5,
      "3006": 4,
      "3007": 7,
      "3008": 6,
      "3009": 3,
      "3010": 2,
      "3011": 1,
      "3012": 6,
      "3013": 4,
      "3014": 6,
      "3015": 6,
      "3016": 3,
      "3017": 2,
      "3018": 4,
      "3019": 1,
      "3020": 4,
      "3021": 4,
      "3022": 5,
      "3024": 4,
      "3025": 1,
      "3026": 5,
      "3027": 2,
      "3028": 3,
      "3029": 5,
      "3030": 2,
      "3031": 5,
      "3032": 4,
      "3033": 2,
      "3034": 2,
      "3035": 1,
      "3037": 3,
      "3039": 3,
      "3040": 1,
      "3041": 1,
      "3042": 3,
      "3043": 1,
      "3044": 3,
      "3045": 1,
      "3046": 1,
      "3047": 3,
      "3049": 2,
      "3050": 2,
      "3051": 3,
      "3053": 3,
      "3054": 1,
      "3055": 2,
      "3056": 3,
      "3057": 1,
      "3058": 1,
      "3059": 2,
      "3060": 3,
      "3061": 4,
      "3062": 2,
      "3063": 1,
      "3064": 2,
      "3065": 3,
      "3066": 5,
      "3067": 2,
      "3068": 3,
      "3069": 3,
      "3070": 3,
      "3071": 1,
      "3072": 1,
      "3073": 2,
      "3076": 2,
      "3077": 2,
      "3078": 1,
      "3079": 3,
      "3080": 1,
      "3081": 3,
      "3082": 3,
      "3083": 1,
      "3084": 2,
      "3085": 1,
      "3086": 1,
      "3087": 3,
      "3089": 4,
      "3090": 1,
      "3091": 6,
      "3092": 2,
      "3093": 2,
      "3094": 4,
      "3095": 3,
      "3096": 4,
      "3097": 6,
      "3098": 3,
      "3099": 3,
      "3100": 1,
      "3101": 2,
      "3102": 4,
      "3103": 3,
      "3104": 2,
      "3105": 3,
      "3106": 2,
      "3107": 2,
      "3108": 2,
      "3109": 4,
      "3110": 6,
      "3111": 7,
      "3112": 4,
      "3113": 5,
      "3115": 2,
      "3116": 1,
      "3117": 3,
      "3118": 2,
      "3119": 1,
      "3120": 2,
      "3121": 5,
      "3122": 3,
      "3123": 6,
      "3124": 4,
      "3125": 3,
      "3126": 2,
      "3127": 5,
      "3128": 1,
      "3129": 6,
      "3131": 3,
      "3132": 2,
      "3133": 2,
      "3135": 1,
      "3136": 1,
      "3138": 2,
      "3140": 1,
      "3141": 1,
      "3142": 1,
      "3143": 3,
      "3145": 1,
      "3148": 2,
      "3149": 3,
      "3150": 1,
      "3151": 3,
      "3152": 1,
      "3154": 1,
      "3155": 2,
      "3156": 4,
      "3157": 1,
      "3158": 1,
      "3159": 5,
      "3160": 2,
      "3161": 2,
      "3162": 1,
      "3163": 2,
      "3164": 1,
      "3166": 2,
      "3167": 2,
      "3168": 3,
      "3170": 2,
      "3171": 1,
      "3172": 3,
      "3173": 3,
      "3174": 2,
      "3175": 1,
      "3176": 4,
      "3177": 5,
      "3178": 4,
      "3179": 3,
      "3180": 4,
      "3181": 4,
      "3182": 5,
      "3183": 5,
      "3184": 2,
      "3185": 1,
      "3186": 8,
      "3187": 1,
      "3188": 6,
      "3189": 3,
      "3190": 3,
      "3191": 4,
      "3192": 4,
      "3193": 6,
      "3194": 2,
      "3195": 3,
      "3196": 6,
      "3197": 2,
      "3198": 4,
      "3199": 2,
      "3200": 7,
      "3201": 4,
      "3202": 5,
      "3203": 5,
      "3204": 4,
      "3205": 3,
      "3206": 5,
      "3207": 6,
      "3208": 3,
      "3209": 6,
      "3210": 4,
      "3211": 4,
      "3212": 5,
      "3213": 3,
      "3214": 4,
      "3215": 2,
      "3218": 2,
      "3219": 3,
      "3220": 2,
      "3222": 4,
      "3223": 3,
      "3224": 3,
      "3225": 2,
      "3226": 2,
      "3227": 3,
      "3228": 1,
      "3229": 1,
      "3230": 2,
      "3231": 3,
      "3232": 3,
      "3233": 3,
      "3234": 1,
      "3235": 2,
      "3236": 1,
      "3237": 1,
      "3238": 3,
      "3239": 2,
      "3240": 1,
      "3242": 4,
      "3243": 1,
      "3244": 1,
      "3246": 1,
      "3247": 1,
      "3248": 3,
      "3249": 1,
      "3251": 1,
      "3257": 1,
      "3258": 1,
      "3260": 1,
      "3261": 1,
      "3262": 2,
      "3263": 2,
      "3264": 1,
      "3266": 1,
      "3267": 2,
      "3268": 1,
      "3269": 1,
      "3271": 1,
      "3274": 3,
      "3275": 1,
      "3276": 2,
      "3278": 1,
      "3280": 1,
      "3281": 2,
      "3282": 2,
      "3283": 3,
      "3284": 2,
      "3285": 1,
      "3286": 1,
      "3287": 3,
      "3288": 2,
      "3289": 2,
      "3290": 2,
      "3291": 3,
      "3292": 2,
      "3293": 1,
      "3294": 1,
      "3295": 5,
      "3296": 2,
      "3297": 1,
      "3299": 4,
      "3300": 1,
      "3302": 1,
      "3304": 3,
      "3306": 2,
      "3307": 3,
      "3308": 1,
      "3310": 1,
      "3313": 3,
      "3314": 2,
      "3316": 2,
      "3317": 1,
      "3318": 1,
      "3319": 1,
      "3320": 1,
      "3322": 1,
      "3324": 1,
      "3327": 1,
      "3328": 1,
      "3336": 1,
      "3340": 1,
      "3341": 1,
      "3356": 1,
      "3358": 1,
      "3359": 1,
      "3362": 2,
      "3366": 1,
      "3373": 1,
      "3377": 1,
      "3384": 2,
      "3410": 1,
      "3418": 1,
      "3437": 1,
      "3443": 1,
      "3446": 1,
      "3451": 2,
      "3468": 1,
      "3475": 1,
      "3477": 1,
      "3478": 1,
      "3487": 1,
      "3491": 1,
      "3493": 1,
      "3499": 1,
      "3511": 1,
      "3520": 1,
      "3527": 2,
      "3528": 1,
      "3539": 2,
      "3551": 1,
      "3559": 1,
      "3576": 1,
      "3911": 1
   },
   "started": "2014-03-01T05:28:53Z",
   "trafficStats": {
      "incomingCompressionRatio": 0.378238525390625,
      "incomingOctetsAppLevel": 8192000,
      "incomingOctetsWebSocketLevel": 3098530,
      "incomingOctetsWireLevel": 3106530,
      "incomingWebSocketFrames": 1000,
      "incomingWebSocketMessages": 1000,
      "incomingWebSocketOverhead": 0.0025818694671344154,
      "outgoingCompressionRatio": 0.380995361328125,
      "outgoingOctetsAppLevel": 8192000,
      "outgoingOctetsWebSocketLevel": 3121114,
      "outgoingOctetsWireLevel": 3125114,
      "outgoingWebSocketFrames": 1000,
      "outgoingWebSocketMessages": 1000,
      "outgoingWebSocketOverhead": 0.0012815936873821333,
      "preopenIncomingOctetsWireLevel": 275,
      "preopenOutgoingOctetsWireLevel": 214
   },
   "txFrameStats": {
      "2": 1000,
      "8": 1
   },
   "txOctetStats": {
      "4": 1,
      "214": 1,
      "2524": 1,
      "2525": 1,
      "2529": 1,
      "2543": 1,
      "2552": 1,
      "2556": 2,
      "2594": 1,
      "2595": 2,
      "2644": 2,
      "2647": 1,
      "2692": 1,
      "2731": 1,
      "2746": 1,
      "2757": 1,
      "2758": 1,
      "2762": 1,
      "2765": 1,
      "2778": 1,
      "2782": 1,
      "2783": 1,
      "2796": 1,
      "2797": 1,
      "2803": 1,
      "2806": 1,
      "2832": 1,
      "2836": 1,
      "2842": 1,
      "2846": 1,
      "2855": 1,
      "2870": 1,
      "2889": 1,
      "2904": 1,
      "2909": 1,
      "2910": 1,
      "2911": 1,
      "2919": 1,
      "2922": 1,
      "2924": 1,
      "2925": 1,
      "2929": 1,
      "2930": 1,
      "2932": 2,
      "2933": 2,
      "2934": 2,
      "2936": 2,
      "2937": 2,
      "2939": 1,
      "2940": 1,
      "2941": 1,
      "2943": 1,
      "2944": 1,
      "2946": 1,
      "2949": 1,
      "2950": 5,
      "2953": 2,
      "2957": 2,
      "2959": 1,
      "2960": 1,
      "2962": 4,
      "2963": 2,
      "2964": 2,
      "2965": 3,
      "2966": 1,
      "2968": 5,
      "2970": 3,
      "2971": 2,
      "2972": 2,
      "2975": 4,
      "2977": 4,
      "2978": 1,
      "2979": 5,
      "2980": 2,
      "2981": 4,
      "2982": 2,
      "2983": 1,
      "2985": 2,
      "2986": 4,
      "2987": 3,
      "2988": 2,
      "2989": 1,
      "2990": 1,
      "2991": 3,
      "2993": 1,
      "2994": 6,
      "2995": 2,
      "2996": 2,
      "2997": 2,
      "2998": 2,
      "2999": 1,
      "3000": 1,
      "3003": 4,
      "3004": 4,
      "3005": 1,
      "3007": 5,
      "3008": 1,
      "3009": 5,
      "3010": 1,
      "3011": 1,
      "3012": 3,
      "3013": 2,
      "3014": 5,
      "3015": 4,
      "3016": 2,
      "3018": 7,
      "3019": 6,
      "3020": 6,
      "3021": 4,
      "3022": 5,
      "3023": 4,
      "3024": 9,
      "3025": 5,
      "3027": 2,
      "3028": 7,
      "3029": 3,
      "3030": 5,
      "3031": 1,
      "3032": 2,
      "3033": 8,
      "3034": 4,
      "3035": 5,
      "3036": 5,
      "3037": 7,
      "3038": 4,
      "3039": 2,
      "3040": 4,
      "3041": 5,
      "3042": 2,
      "3043": 6,
      "3044": 2,
      "3045": 5,
      "3046": 6,
      "3047": 2,
      "3048": 6,
      "3049": 3,
      "3050": 5,
      "3051": 1,
      "3052": 3,
      "3053": 1,
      "3054": 1,
      "3055": 3,
      "3056": 4,
      "3057": 3,
      "3058": 3,
      "3059": 1,
      "3060": 1,
      "3062": 4,
      "3064": 2,
      "3065": 2,
      "3067": 1,
      "3068": 3,
      "3069": 2,
      "3071": 1,
      "3073": 4,
      "3074": 1,
      "3075": 2,
      "3076": 1,
      "3077": 2,
      "3078": 1,
      "3079": 3,
      "3080": 2,
      "3081": 3,
      "3082": 2,
      "3083": 1,
      "3084": 5,
      "3085": 2,
      "3087": 1,
      "3088": 2,
      "3089": 2,
      "3090": 2,
      "3091": 1,
      "3092": 4,
      "3093": 2,
      "3094": 2,
      "3095": 2,
      "3097": 4,
      "3098": 4,
      "3099": 3,
      "3100": 2,
      "3101": 1,
      "3103": 3,
      "3105": 2,
      "3107": 2,
      "3108": 2,
      "3109": 1,
      "3110": 1,
      "3111": 4,
      "3112": 4,
      "3113": 4,
      "3114": 3,
      "3115": 3,
      "3116": 4,
      "3117": 1,
      "3118": 1,
      "3119": 3,
      "3120": 5,
      "3121": 6,
      "3122": 3,
      "3123": 2,
      "3124": 3,
      "3125": 4,
      "3126": 2,
      "3127": 3,
      "3128": 2,
      "3129": 7,
      "3130": 1,
      "3131": 4,
      "3132": 3,
      "3133": 4,
      "3134": 5,
      "3135": 1,
      "3136": 3,
      "3137": 4,
      "3138": 1,
      "3139": 6,
      "3140": 3,
      "3141": 5,
      "3142": 2,
      "3143": 5,
      "3144": 4,
      "3145": 2,
      "3146": 2,
      "3147": 3,
      "3148": 2,
      "3149": 3,
      "3150": 3,
      "3151": 3,
      "3152": 3,
      "3153": 1,
      "3155": 1,
      "3156": 3,
      "3157": 2,
      "3158": 3,
      "3160": 1,
      "3161": 1,
      "3162": 3,
      "3163": 3,
      "3164": 1,
      "3165": 1,
      "3167": 2,
      "3168": 1,
      "3169": 2,
      "3170": 2,
      "3171": 4,
      "3172": 1,
      "3174": 1,
      "3175": 3,
      "3176": 2,
      "3178": 2,
      "3179": 2,
      "3180": 2,
      "3182": 3,
      "3184": 4,
      "3185": 1,
      "3186": 2,
      "3187": 1,
      "3188": 1,
      "3189": 2,
      "3190": 2,
      "3192": 3,
      "3194": 3,
      "3195": 1,
      "3196": 3,
      "3197": 3,
      "3198": 1,
      "3199": 1,
      "3200": 5,
      "3201": 6,
      "3202": 6,
      "3203": 2,
      "3204": 3,
      "3205": 6,
      "3206": 1,
      "3207": 10,
      "3208": 2,
      "3209": 3,
      "3210": 4,
      "3211": 3,
      "3212": 4,
      "3213": 3,
      "3214": 4,
      "3215": 4,
      "3216": 9,
      "3217": 1,
      "3218": 5,
      "3219": 5,
      "3220": 7,
      "3221": 6,
      "3222": 4,
      "3223": 2,
      "3224": 4,
      "3225": 4,
      "3226": 8,
      "3227": 5,
      "3228": 5,
      "3229": 3,
      "3230": 6,
      "3231": 1,
      "3232": 5,
      "3233": 4,
      "3234": 2,
      "3235": 2,
      "3236": 3,
      "3237": 4,
      "3239": 2,
      "3240": 5,
      "3241": 4,
      "3242": 2,
      "3243": 6,
      "3244": 3,
      "3245": 2,
      "3246": 1,
      "3247": 4,
      "3250": 2,
      "3251": 3,
      "3252": 1,
      "3253": 2,
      "3254": 1,
      "3256": 1,
      "3260": 2,
      "3261": 1,
      "3262": 1,
      "3263": 4,
      "3265": 2,
      "3267": 2,
      "3269": 1,
      "3271": 3,
      "3272": 1,
      "3273": 2,
      "3275": 1,
      "3276": 1,
      "3282": 1,
      "3283": 2,
      "3284": 1,
      "3285": 1,
      "3286": 1,
      "3287": 3,
      "3288": 1,
      "3289": 1,
      "3290": 1,
      "3291": 2,
      "3292": 2,
      "3293": 2,
      "3294": 1,
      "3295": 1,
      "3296": 4,
      "3297": 1,
      "3299": 3,
      "3300": 2,
      "3302": 4,
      "3303": 2,
      "3305": 5,
      "3306": 5,
      "3307": 3,
      "3308": 4,
      "3309": 1,
      "3310": 2,
      "3311": 3,
      "3312": 1,
      "3314": 4,
      "3315": 3,
      "3316": 2,
      "3317": 1,
      "3318": 1,
      "3319": 2,
      "3321": 2,
      "3322": 2,
      "3323": 1,
      "3326": 1,
      "3327": 2,
      "3331": 1,
      "3332": 1,
      "3333": 1,
      "3339": 1,
      "3344": 1,
      "3345": 1,
      "3359": 1,
      "3361": 1,
      "3362": 1,
      "3366": 2,
      "3371": 1,
      "3378": 1,
      "3381": 1,
      "3388": 2,
      "3413": 1,
      "3421": 1,
      "3440": 1,
      "3444": 1,
      "3447": 1,
      "3451": 1,
      "3452": 1,
      "3469": 1,
      "3475": 1,
      "3479": 1,
      "3480": 1,
      "3487": 1,
      "3492": 1,
      "3493": 1,
      "3500": 1,
      "3513": 1,
      "3519": 1,
      "3527": 1,
      "3528": 1,
      "3529": 1,
      "3536": 1,
      "3538": 1,
      "3547": 1,
      "3557": 1,
      "3575": 1,
      "3908": 1
   },
   "wasClean": true,
   "wasCloseHandshakeTimeout": false,
   "wasNotCleanReason": null,
   "wasOpenHandshakeTimeout": false,
   "wasServerConnectionDropTimeout": false,
   "wirelog": [
      [
         "RO",
         [
            275,
            "474554202f72756e436173653f636173653d333331266167656e743d73707261792d776562736f636b65742d636c69656e7420485454502f312e310d0a486f73 ..."
         ]
      ],
      [
         "TO",
         [
            214,
            "485454502f312e312031303120537769746368696e672050726f746f636f6c730d0a5365727665723a204175746f6261686e5465737453756974652f302e352e ..."
         ],
         false
      ],
      [
         "WLM",
         false
      ],
      [
         "TI",
         480
      ],
      [
         "WLM",
         true
      ],
      [
         "TF",
         [
            2,
            "0x03e8"
         ],
         8,
         true,
         0,
         null,
         null,
         null,
         false
      ],
      [
         "TO",
         [
            4,
            "880203e8"
         ],
         false
      ],
      [
         "RO",
         [
            1,
            "88"
         ]
      ],
      [
         "RO",
         [
            7,
            "82235d45a020b5"
         ]
      ],
      [
         "RF",
         [
            2,
            "0x03e8"
         ],
         8,
         true,
         0,
         true,
         "235d45a0"
      ]
   ]
}